{
  "disclaimer": "Usage subject to terms: https://openexchangerates.org/terms",
  "license": "https://openexchangerates.org/license",
  "timestamp": 1521503999,
  "base": "USD",
  "rates": {
    "AED": 3.673014,
    "AFN": 69.49803,
    "ALL": 105.7,
    "AMD": 478.507004,
    "ANG": 1.779699,
    "AOA": 214.384,
    "ARS": 20.1945,
    "AUD": 1.297536,
    "AWG": 1.78625,
    "AZN": 1.7025,
    "BAM": 1.587034,
    "BBD": 2,
    "BDT": 83.234871,
    "BGN": 1.585018,
    "BHD": 0.377002,
    "BIF": 1754.963054,
    "BMD": 1,
    "BND": 1.317528,
    "BOB": 6.905008,
    "BRL": 3.2855,
    "BSD": 1,
    "BTC": 0.000116417692,
    "BTN": 64.902793,
    "BWP": 9.619412,
    "BYN": 1.963244,
    "BZD": 2.004048,
    "CAD": 1.308358,
    "CDF": 1615,
    "CHF": 0.951197,
    "CLF": 0.022625,
    "CLP": 609.3,
    "CNH": 6.324383,
    "CNY": 6.333517,
    "COP": 2860,
    "CRC": 566.585059,
    "CUC": 1,
    "CUP": 25.5,
    "CVE": 89.875,
    "CZK": 20.602093,
    "DJF": 177.1,
    "DKK": 6.038283,
    "DOP": 49.409299,
    "DZD": 113.963976,
    "EGP": 17.636,
    "ERN": 14.996667,
    "ETB": 27.42916,
    "EUR": 0.8106,
    "FJD": 2.025551,
    "FKP": 0.713,
    "GBP": 0.713,
    "GEL": 2.444502,
    "GGP": 0.713,
    "GHS": 4.417136,
    "GIP": 0.713,
    "GMD": 47.455,
    "GNF": 8999.95,
    "GTQ": 7.39557,
    "GYD": 206.508743,
    "HKD": 7.84292,
    "HNL": 23.61012,
    "HRK": 6.02446,
    "HTG": 64.502513,
    "HUF": 252.3215,
    "IDR": 13770.980429,
    "ILS": 3.47314,
    "IMP": 0.713,
    "INR": 65.2201,
    "IQD": 1187.990579,
    "IRR": 37571.52369,
    "ISK": 99.14,
    "JEP": 0.713,
    "JMD": 127.209149,
    "JOD": 0.709001,
    "JPY": 106.018,
    "KES": 101.294639,
    "KGS": 68.221949,
    "KHR": 3992.35,
    "KMF": 399.301594,
    "KPW": 900,
    "KRW": 1073.3,
    "KWD": 0.299915,
    "KYD": 0.830886,
    "KZT": 320.134681,
    "LAK": 8297.133333,
    "LBP": 1513.433333,
    "LKR": 155.86012,
    "LRD": 131.229411,
    "LSL": 12.002177,
    "LYD": 1.331537,
    "MAD": 9.165976,
    "MDL": 16.53176,
    "MGA": 3151.96129,
    "MKD": 49.901,
    "MMK": 1334.860206,
    "MNT": 2393.74936,
    "MOP": 8.054516,
    "MRO": 355.5,
    "MRU": 35.35,
    "MUR": 33.352,
    "MVR": 15.460011,
    "MWK": 726.537145,
    "MXN": 18.71329,
    "MYR": 3.916502,
    "MZN": 62.056957,
    "NAD": 12.041864,
    "NGN": 359.77934,
    "NIO": 31.131705,
    "NOK": 7.723091,
    "NPR": 103.855544,
    "NZD": 1.381025,
    "OMR": 0.385017,
    "PAB": 1,
    "PEN": 3.273726,
    "PGK": 3.230861,
    "PHP": 52.1045,
    "PKR": 110.54343,
    "PLN": 3.423544,
    "PYG": 5519.1,
    "QAR": 3.641124,
    "RON": 3.781591,
    "RSD": 95.853122,
    "RUB": 57.7635,
    "RWF": 859.354122,
    "SAR": 3.74995,
    "SBD": 7.752334,
    "SCR": 13.788542,
    "SDG": 18.086534,
    "SEK": 8.165001,
    "SGD": 1.316528,
    "SHP": 0.713,
    "SLL": 7664.007735,
    "SOS": 580.398872,
    "SRD": 7.468,
    "SSP": 130.2634,
    "STD": 19883.609374,
    "STN": 19.96,
    "SVC": 8.724332,
    "SYP": 514.98999,
    "SZL": 12.031896,
    "THB": 31.205,
    "TJS": 8.793811,
    "TMT": 3.50998,
    "TND": 2.392099,
    "TOP": 2.210732,
    "TRY": 3.944153,
    "TTD": 6.716259,
    "TWD": 29.155,
    "TZS": 2257.15,
    "UAH": 26.36705,
    "UGX": 3643.358069,
    "USD": 1,
    "UYU": 28.370943,
    "UZS": 8142.033333,
    "VEF": 36650,
    "VND": 22767.86534,
    "VUV": 106.372164,
    "WST": 2.539405,
    "XAF": 531.718744,
    "XAG": 0.06122771,
    "XAU": 0.00075922,
    "XCD": 2.70255,
    "XDR": 0.688832,
    "XOF": 531.718744,
    "XPD": 0.0010086,
    "XPF": 96.73031,
    "XPT": 0.00104823,
    "YER": 250.294142,
    "ZAR": 12.022981,
    "ZMW": 9.446955,
    "ZWL": 322.355011
  }
}