{
  "disclaimer": "Usage subject to terms: https://openexchangerates.org/terms",
  "license": "https://openexchangerates.org/license",
  "timestamp": 1522972799,
  "base": "USD",
  "rates": {
    "AED": 3.673097,
    "AFN": 69.548409,
    "ALL": 105.701667,
    "AMD": 480.502877,
    "ANG": 1.785645,
    "AOA": 214.3575,
    "ARS": 20.189,
    "AUD": 1.304013,
    "AWG": 1.785503,
    "AZN": 1.7025,
    "BAM": 1.593223,
    "BBD": 2,
    "BDT": 83.253132,
    "BGN": 1.59825,
    "BHD": 0.377061,
    "BIF": 1766.210443,
    "BMD": 1,
    "BND": 1.316942,
    "BOB": 6.910596,
    "BRL": 3.344781,
    "BSD": 1,
    "BTC": 0.000147371257,
    "BTN": 65.008819,
    "BWP": 9.591309,
    "BYN": 1.963091,
    "BZD": 2.010662,
    "CAD": 1.277146,
    "CDF": 1614.661462,
    "CHF": 0.962351,
    "CLF": 0.02214,
    "CLP": 604.235122,
    "CNH": 6.306531,
    "CNY": 6.30465,
    "COP": 2817.460317,
    "CRC": 567.037559,
    "CUC": 1,
    "CUP": 25.5,
    "CVE": 90.45,
    "CZK": 20.68241,
    "DJF": 177,
    "DKK": 6.080213,
    "DOP": 49.483412,
    "DZD": 114.254,
    "EGP": 17.6845,
    "ERN": 14.996667,
    "ETB": 27.485429,
    "EUR": 0.816407,
    "FJD": 2.043351,
    "FKP": 0.713963,
    "GBP": 0.713963,
    "GEL": 2.425377,
    "GGP": 0.713963,
    "GHS": 4.428383,
    "GIP": 0.713963,
    "GMD": 47.3,
    "GNF": 9020.233333,
    "GTQ": 7.42003,
    "GYD": 207.03273,
    "HKD": 7.84925,
    "HNL": 23.707566,
    "HRK": 6.0671,
    "HTG": 64.252396,
    "HUF": 254.086667,
    "IDR": 13770.980429,
    "ILS": 3.529055,
    "IMP": 0.713963,
    "INR": 64.8715,
    "IQD": 1190.370579,
    "IRR": 37636.02369,
    "ISK": 99.23,
    "JEP": 0.713963,
    "JMD": 124.951347,
    "JOD": 0.7085,
    "JPY": 107.10836667,
    "KES": 101.0985,
    "KGS": 68.336352,
    "KHR": 4035.003333,
    "KMF": 402.498446,
    "KPW": 900,
    "KRW": 1062.54,
    "KWD": 0.300109,
    "KYD": 0.833608,
    "KZT": 319.983991,
    "LAK": 8304.283333,
    "LBP": 1513.6,
    "LKR": 155.67134,
    "LRD": 131.751267,
    "LSL": 11.911959,
    "LYD": 1.331348,
    "MAD": 9.2331,
    "MDL": 16.364032,
    "MGA": 3221.383333,
    "MKD": 50.2705,
    "MMK": 1331.510206,
    "MNT": 2387.99936,
    "MOP": 8.087069,
    "MRO": 355.5,
    "MRU": 35.39,
    "MUR": 33.572,
    "MVR": 15.404937,
    "MWK": 724.606611,
    "MXN": 18.2342,
    "MYR": 3.866529,
    "MZN": 61.130857,
    "NAD": 11.944979,
    "NGN": 359.71734,
    "NIO": 31.186866,
    "NOK": 7.838825,
    "NPR": 104.018371,
    "NZD": 1.377054,
    "OMR": 0.385011,
    "PAB": 1,
    "PEN": 3.226729,
    "PGK": 3.242919,
    "PHP": 51.988566,
    "PKR": 115.756711,
    "PLN": 3.424587,
    "PYG": 5555.4,
    "QAR": 3.641481,
    "RON": 3.805814,
    "RSD": 96.433,
    "RUB": 57.692,
    "RWF": 863.722767,
    "SAR": 3.750244,
    "SBD": 7.783984,
    "SCR": 13.455,
    "SDG": 18.136019,
    "SEK": 8.426781,
    "SGD": 1.316481,
    "SHP": 0.713963,
    "SLL": 7664.007735,
    "SOS": 577.783837,
    "SRD": 7.468,
    "SSP": 130.2634,
    "STD": 19952.458984,
    "STN": 20.1,
    "SVC": 8.752898,
    "SYP": 514.98999,
    "SZL": 11.907789,
    "THB": 31.2815,
    "TJS": 8.827718,
    "TMT": 3.499986,
    "TND": 2.405301,
    "TOP": 2.237882,
    "TRY": 4.043565,
    "TTD": 6.73576,
    "TWD": 29.253,
    "TZS": 2260.1,
    "UAH": 26.273044,
    "UGX": 3694.25,
    "USD": 1,
    "UYU": 28.241571,
    "UZS": 8114.6,
    "VEF": 40241.5117,
    "VND": 22799.76534,
    "VUV": 106.322163,
    "WST": 2.528438,
    "XAF": 535.528042,
    "XAG": 0.06088717,
    "XAU": 0.00075143,
    "XCD": 2.70255,
    "XDR": 0.689083,
    "XOF": 535.528042,
    "XPD": 0.00110318,
    "XPF": 97.423298,
    "XPT": 0.0010947,
    "YER": 250.306642,
    "ZAR": 11.996409,
    "ZMW": 9.427982,
    "ZWL": 322.355011
  }
}